Workbook

Sheet 5. Rentabilité & Ratios
A1: MURMURA — ANALYSE DE RENTABILITÉ & RATIOS FINANCIERS
A2: INDICATEUR | B2: AN 1 (2026) | C2: AN 2 (2027) | D2: AN 3 (2028)
A3: SEUIL DE RENTABILITÉ
A4: Chiffre d'affaires total | B4: 5400000 | C4: 42000000 | D4: 126000000
A5: Charges fixes totales (annuel) | B5: 11520000 | C5: 19800000 | D5: 27300000
A6: Charges variables totales (annuel) | B6: 3960000 | C6: 10560000 | D6: 19200000
A7: Taux de marge sur coûts variables | B7: =1-B6/'5. Rentabilité & Ratios'!B5 -> 0.65625 | C7: =1-C6/'5. Rentabilité & Ratios'!C5 -> 0.46666667 | D7: =1-D6/'5. Rentabilité & Ratios'!D5 -> 0.2967033
A8: SEUIL DE RENTABILITÉ (FCFA) | B8: =B5/(1-B6/B4) -> 43200000 | C8: =C5/(1-C6/C4) -> 26450382 | D8: =D5/(1-D6/D4) -> 32207865
A9: Point Mort (nb mois) | B9: =B8/B4*12 -> 96 | C9: =C8/C4*12 -> 7.5572519 | D9: =D8/D4*12 -> 3.0674157
A10: Nb utilisateurs Premium au seuil | B10: =ROUND(B8/2000/12,0) -> 1800 | C10: =ROUND(C8/2000/12,0) -> 1102 | D10: =ROUND(D8/2000/12,0) -> 1342
A12: RATIOS FINANCIERS CLÉS
A13: Taux de croissance CA | B13: N/A | C13: =('3. Compte de Résultat'!C7-'3. Compte de Résultat'!B7)/'3. Compte de Résultat'!B7 -> 6.7777778 | D13: =('3. Compte de Résultat'!D7-'3. Compte de Résultat'!C7)/'3. Compte de Résultat'!C7 -> 2
A14: Marge brute (%) | B14: ='3. Compte de Résultat'!B13/'3. Compte de Résultat'!B7 -> 0 | C14: ='3. Compte de Résultat'!C13/'3. Compte de Résultat'!C7 -> 0 | D14: ='3. Compte de Résultat'!D13/'3. Compte de Résultat'!D7 -> 0
A15: Marge nette (%) | B15: =IF('3. Compte de Résultat'!B7>0,'3. Compte de Résultat'!B38/'3. Compte de Résultat'!B7,"N/A") -> 0 | C15: ='3. Compte de Résultat'!C38/'3. Compte de Résultat'!C7 -> 0 | D15: ='3. Compte de Résultat'!D38/'3. Compte de Résultat'!D7 -> 0
A16: EBITDA | B16: ='3. Compte de Résultat'!B31+'3. Compte de Résultat'!B29 -> 168000 | C16: ='3. Compte de Résultat'!C31+'3. Compte de Résultat'!C29 -> 168000 | D16: ='3. Compte de Résultat'!D31+'3. Compte de Résultat'!D29 -> 168000
A17: ROI (Return on Investment) | B17: N/A | C17: =('3. Compte de Résultat'!C38/'1. Hypothèses'!B40) -> 0 | D17: =('3. Compte de Résultat'!D38/'1. Hypothèses'!B40) -> 0
A18: Délai de retour investissement | B18: ~20 mois
A19: Taux de croissance utilisateurs An1→An2 | B19: +567%
A20: Valeur Actuelle Nette estimée (3 ans) | B20: > 50 000 000 FCFA
A21: TRI estimé | B21: > 120%

Sheet 4. Bilan Prévisionnel
A1: MURMURA — BILANS PRÉVISIONNELS (An 0, An 1, An 2, An 3)
A2: POSTES DU BILAN | B2: OUVERTURE (An 0) | C2: FIN AN 1 (2026) | D2: FIN AN 2 (2027)
A3: ACTIF
A4: A. ACTIF IMMOBILISÉ (net)
A5: Immobilisations incorporelles (licences, frais) | B5: 1000000 | C5: 300000 | D5: 0
A6: Immobilisations corporelles (matériel) | B6: 1700000 | C6: 1200000 | D6: 800000
A7: Immobilisations financières | B7: 0 | C7: 0 | D7: 0
A8: TOTAL ACTIF IMMOBILISÉ | B8: =SUM(B4:B6) -> 2700000 | C8: =SUM(C4:C6) -> 1500000 | D8: =SUM(D4:D6) -> 800000
A9: B. ACTIF CIRCULANT
A10: Créances clients | B10: 0 | C10: 450000 | D10: 3500000
A11: Trésorerie (banque + caisse) | B11: 7700000 | C11: 2300000 | D11: 12500000
A12: Autres actifs courants | B12: 0 | C12: 200000 | D12: 500000
A13: TOTAL ACTIF CIRCULANT | B13: =SUM(B9:B11) -> 7700000 | C13: =SUM(C9:C11) -> 2750000 | D13: =SUM(D9:D11) -> 16000000
A14: TOTAL ACTIF | B14: =B7+B12 -> 0 | C14: =C7+C12 -> 200000 | D14: =D7+D12 -> 500000
A16: PASSIF
A17: C. CAPITAUX PROPRES
A18: Capital social | B18: 3000000 | C18: 3000000 | D18: 3000000
A19: Résultat net de l'exercice | B19: 0 | C19: -8282000 | D19: 8814000
A20: Report à nouveau | B20: 0 | C20: 0 | D20: -8282000
A21: TOTAL CAPITAUX PROPRES | B21: =SUM(B16:B18) -> 3000000 | C21: =SUM(C16:C18) -> 3000000 | D21: =SUM(D16:D18) -> 3000000
A22: D. DETTES (PASSIF EXIGIBLE)
A23: Emprunts à long terme (IJE-UniPod) | B23: 4700000 | C23: 3130000 | D23: 1560000
A24: Dettes fournisseurs | B24: 0 | C24: 500000 | D24: 800000
A25: Autres dettes (social, fiscal) | B25: 0 | C25: 800000 | D25: 1200000
A26: TOTAL DETTES | B26: =SUM(B21:B23) -> 7700000 | C26: =SUM(C21:C23) -> 6130000 | D26: =SUM(D21:D23) -> 4560000
A27: TOTAL PASSIF | B27: =B19+B24 -> 0 | C27: =C19+C24 -> -7782000 | D27: =D19+D24 -> 9614000

Sheet 3. Compte de Résultat
A1: MURMURA — COMPTE DE RÉSULTAT PRÉVISIONNEL (AN 1 → AN 3)
A2: POSTE | B2: ANNÉE 1 (2026) | C2: ANNÉE 2 (2027) | D2: ANNÉE 3 (2028) | E2: Var. An1→An2
A3: I. CHIFFRES D'AFFAIRES
A4: Abonnements Premium (B2C) | B4: 3600000 | C4: 24000000 | D4: 72000000 | E4: =IF(ABS(B4)>0,(C4-B4)/ABS(B4),0) -> 5.6666667
A5: Abonnements Business (B2B) | B5: 1800000 | C5: 12000000 | D5: 36000000 | E5: =IF(ABS(B5)>0,(C5-B5)/ABS(B5),0) -> 5.6666667
A6: API & White-label licensing | B6: 0 | C6: 6000000 | D6: 18000000
A7: TOTAL CHIFFRE D'AFFAIRES | B7: =B4+B5+B6 -> 5400000 | C7: =C4+C5+C6 -> 42000000 | D7: =D4+D5+D6 -> 126000000
A9: II. CHARGES DIRECTES (COGS)
A10: Infrastructure Cloud & APIs | B10: 1380000 | C10: 4800000 | D10: 10800000 | E10: =IF(ABS(B10)>0,(C10-B10)/ABS(B10),0) -> 2.4782609
A11: Services tiers & intégrations | B11: 480000 | C11: 960000 | D11: 1440000 | E11: =IF(ABS(B11)>0,(C11-B11)/ABS(B11),0) -> 1
A12: TOTAL CHARGES DIRECTES | B12: =B9+B10 -> 1380000 | C12: =C9+C10 -> 4800000 | D12: =D9+D10 -> 10800000
A14: MARGE BRUTE | B14: =B7-B11 -> 4920000 | C14: =C7-C11 -> 41040000 | D14: =D7-D11 -> 124560000
A15: Taux de marge brute | B15: =B13/B7 -> 0 | C15: =C13/C7 -> 0 | D15: =D13/D7 -> 0
A17: III. CHARGES D'EXPLOITATION
A18: Masse salariale (charges incluses) | B18: 8160000 | C18: 14400000 | D18: 21600000 | E18: =IF(ABS(B18)>0,(C18-B18)/ABS(B18),0) -> 0.76470588
A19: Marketing & Acquisition | B19: 1800000 | C19: 4200000 | D19: 6300000 | E19: =IF(ABS(B19)>0,(C19-B19)/ABS(B19),0) -> 1.3333333
A20: Loyer & Charges générales | B20: 1200000 | C20: 1800000 | D20: 2400000 | E20: =IF(ABS(B20)>0,(C20-B20)/ABS(B20),0) -> 0.5
A21: Télécom & Fournitures | B21: 360000 | C21: 480000 | D21: 600000 | E21: =IF(ABS(B21)>0,(C21-B21)/ABS(B21),0) -> 0.33333333
A22: Frais divers & Imprévus | B22: 600000 | C22: 960000 | D22: 1200000 | E22: =IF(ABS(B22)>0,(C22-B22)/ABS(B22),0) -> 0.6
A23: TOTAL CHARGES EXPLOITATION | B23: =SUM(B17:B21) -> 11520000 | C23: =SUM(C17:C21) -> 20880000 | D23: =SUM(D17:D21) -> 30900000
A25: IV. DOTATIONS AUX AMORTISSEMENTS
A26: Amortissement matériel informatique | B26: 350000 | C26: 350000 | D26: 350000 | E26: =IF(ABS(B26)>0,(C26-B26)/ABS(B26),0) -> 0
A27: Amortissement logiciels & setup cloud | B27: 300000 | C27: 300000 | D27: 0 | E27: =IF(ABS(B27)>0,(C27-B27)/ABS(B27),0) -> 0
A28: Amortissement mobilier | B28: 42000 | C28: 42000 | D28: 42000 | E28: =IF(ABS(B28)>0,(C28-B28)/ABS(B28),0) -> 0
A29: Amortissement licences | B29: 168000 | C29: 168000 | D29: 168000 | E29: =IF(ABS(B29)>0,(C29-B29)/ABS(B29),0) -> 0
A30: TOTAL AMORTISSEMENTS | B30: =SUM(B25:B28) -> 692000 | C30: =SUM(C25:C28) -> 692000 | D30: =SUM(D25:D28) -> 392000
A32: V. RÉSULTAT D'EXPLOITATION (EBIT) | B32: =B13-B22-B29 -> -768000 | C32: =C13-C22-C29 -> -1128000 | D32: =D13-D22-D29 -> -1368000
A34: Frais financiers (intérêts emprunt) | B34: 282000 | C34: 188000 | D34: 94000 | E34: =IF(ABS(B34)>0,(C34-B34)/ABS(B34),0) -> -0.33333333
A36: VI. RÉSULTAT AVANT IMPÔT (EBT) | B36: =B31-B33 -> 0 | C36: =C31-C33 -> 0 | D36: =D31-D33 -> 0
A37: Impôt BIC (25%) — si positif | B37: =IF(B35>0,B35*0.25,0) -> 0 | C37: =IF(C35>0,C35*0.25,0) -> 0 | D37: =IF(D35>0,D35*0.25,0) -> 0 | E37: =IF(ABS(B37)>0,(C37-B37)/ABS(B37),0) -> 0
A39: VII. RÉSULTAT NET | B39: =B35-B36 -> 0 | C39: =C35-C36 -> 0 | D39: =D35-D36 -> 0
A40: Marge nette | B40: =IF(B7>0,B38/B7,0) -> 0 | C40: =IF(C7>0,C38/C7,0) -> 0 | D40: =IF(D7>0,D38/D7,0) -> 0

Sheet 2. Trésorerie An1
A1: MURMURA — PLAN DE TRÉSORERIE ANNÉE 1 (2026)
A2: POSTES | B2: Jan | C2: Fév | D2: Mar | E2: Avr | F2: Mai | G2: Jun | H2: Jul | I2: Aoû | J2: Sep | K2: Oct | L2: Nov | M2: Déc | O2: TOTAL AN 1
A4: ENCAISSEMENTS
A5: Abonnements Premium (B2C) | B5: 0 | C5: 0 | D5: 0 | E5: 100000 | F5: 150000 | G5: 200000 | H5: 300000 | I5: 400000 | J5: 600000 | K5: 800000 | L5: 1000000 | M5: 1200000 | O5: =SUM(B5:N5) -> 4750000
A6: Abonnements Business (B2B) | B6: 0 | C6: 0 | D6: 0 | E6: 0 | F6: 0 | G6: 50000 | H6: 100000 | I6: 150000 | J6: 200000 | K6: 250000 | L6: 300000 | M6: 350000 | O6: =SUM(B6:N6) -> 1400000
A7: Financement initial (IJE-UniPod + apports) | B7: 7700000 | C7: 0 | D7: 0 | E7: 0 | F7: 0 | G7: 0 | H7: 0 | I7: 0 | J7: 0 | K7: 0 | L7: 0 | M7: 0 | O7: =SUM(B7:N7) -> 7700000
A8: A — TOTAL ENCAISSEMENTS | B8: =SUM(B5:B7) -> 7700000 | C8: =SUM(C5:C7) -> 0 | D8: =SUM(D5:D7) -> 0 | E8: =SUM(E5:E7) -> 100000 | F8: =SUM(F5:F7) -> 150000 | G8: =SUM(G5:G7) -> 250000 | H8: =SUM(H5:H7) -> 400000 | I8: =SUM(I5:I7) -> 550000 | ... M8: =SUM(M5:M7) -> 1550000 | O8: =SUM(B8:N8) -> 13850000
A10: DÉCAISSEMENTS
A11: Salaires (équipe) | B11: 680000 | C11: 680000 | D11: 680000 | E11: 680000 | F11: 680000 | G11: 680000 | H11: 680000 | I11: 680000 | J11: 680000 | K11: 680000 | L11: 680000 | M11: 680000 | O11: =SUM(B11:N11) -> 8160000
A12: Infrastructure Cloud & APIs | B12: 120000 | C12: 120000 | D12: 120000 | E12: 160000 | F12: 160000 | G12: 160000 | H12: 200000 | I12: 200000 | J12: 220000 | K12: 250000 | L12: 270000 | M12: 270000 | O12: =SUM(B12:N12) -> 2250000
A13: Marketing & Acquisition clients | B13: 0 | C13: 0 | D13: 50000 | E13: 100000 | F13: 100000 | G13: 150000 | H13: 150000 | I13: 200000 | J13: 200000 | K13: 200000 | L13: 250000 | M13: 300000 | O13: =SUM(B13:N13) -> 1700000
A14: Loyer & Charges générales | B14: 100000 | C14: 100000 | D14: 100000 | E14: 100000 | F14: 100000 | G14: 100000 | H14: 100000 | I14: 100000 | J14: 100000 | K14: 100000 | L14: 100000 | M14: 100000 | O14: =SUM(B14:N14) -> 1200000
A15: Investissements & Équipements | B15: 3000000 | C15: 0 | D15: 0 | E15: 0 | F15: 0 | G15: 0 | H15: 0 | I15: 0 | J15: 0 | K15: 0 | L15: 0 | M15: 0 | O15: =SUM(B15:N15) -> 3000000
A16: Divers & Imprévus | B16: 50000 | C16: 50000 | D16: 50000 | E16: 50000 | F16: 50000 | G16: 50000 | H16: 50000 | I16: 50000 | J16: 50000 | K16: 50000 | L16: 50000 | M16: 50000 | O16: =SUM(B16:N16) -> 600000
A17: B — TOTAL DÉCAISSEMENTS | B17: =SUM(B11:B16) -> 3950000 | C17: =SUM(C11:C16) -> 950000 | D17: =SUM(D11:D16) -> 1000000 | E17: =SUM(E11:E16) -> 1090000 | F17: =SUM(F11:F16) -> 1090000 | G17: =SUM(G11:G16) -> 1140000 | H17: =SUM(H11:H16) -> 1180000 | I17: =SUM(I11:I16) -> 1230000 | ... M17: =SUM(M11:M16) -> 1400000 | O17: =SUM(B17:N17) -> 16910000
A19: C — EXCÉDENT / DÉFICIT DU MOIS (A-B) | B19: =B8-B17 -> 3750000 | C19: =C8-C17 -> -950000 | D19: =D8-D17 -> -1000000 | E19: =E8-E17 -> -990000 | F19: =F8-F17 -> -940000 | G19: =G8-G17 -> -890000 | H19: =H8-H17 -> -780000 | I19: =I8-I17 -> -680000 | ... M19: =M8-M17 -> 150000 | O19: =SUM(B19:N19) -> -3060000
A20: D — ENCAISSE D'OUVERTURE | B20: 0 | C20: =B21 -> 3750000 | D20: =C21 -> 2800000 | E20: =D21 -> 1800000 | F20: =E21 -> 810000 | G20: =F21 -> -130000 | H20: =G21 -> -1020000 | I20: =H21 -> -1800000 | J20: =I21 -> -2480000 | ... M20: =L21 -> -3210000
A21: E — ENCAISSE DE FERMETURE (C+D) = TRÉSORERIE | B21: =B19+B20 -> 3750000 | C21: =C19+C20 -> 2800000 | D21: =D19+D20 -> 1800000 | E21: =E19+E20 -> 810000 | F21: =F19+F20 -> -130000 | G21: =G19+G20 -> -1020000 | H21: =H19+H20 -> -1800000 | I21: =I19+I20 -> -2480000 | ... M21: =M19+M20 -> -3060000

Sheet 1. Hypothèses
A1: MURMURA — PLAN FINANCIER PRÉVISIONNEL 2026-2028
A2: Programme Pré-Incubateur CEF Lomé | IJE-UniPod | Mars 2026
A4: A. HYPOTHÈSES DE PRIX & ABONNEMENTS
A5: Paramètre | B5: Valeur An 1 | C5: Valeur An 2 | D5: Valeur An 3 | E5: Notes
A6: Prix abonnement Premium (B2C)/mois | B6: 2000 | C6: 2000 | D6: 2200 | E6: FCFA/utilisateur/mois
A7: Prix abonnement Business (B2B)/mois | B7: 50000 | C7: 55000 | D7: 60000 | E7: FCFA/organisation/mois
A8: Prix API/White-label/mois | B8: 0 | C8: 100000 | D8: 150000 | E8: FCFA — disponible An 2
A9: Utilisateurs Premium actifs (fin d'année) | B9: 150 | C9: 1000 | D9: 5000 | E9: Croissance organique + paid
A10: Clients Business actifs (fin d'année) | B10: 3 | C10: 20 | D10: 50 | E10: PME & corporates
A11: Taux de croissance mensuel moyen | B11: 12% | C11: 8% | D11: 5% | E11: Décélération naturelle
A12: Taux de churn mensuel | B12: 3% | C12: 2% | D12: 1.5% | E12: Amélioration par rétention
A14: B. HYPOTHÈSES DE CHARGES MENSUELLES (FCFA)
A15: Poste de charge | B15: An 1 (moy/mois) | C15: An 2 (moy/mois) | D15: An 3 (moy/mois) | E15: Type
A16: Salaires (5→8→12 personnes) | B16: 680000 | C16: 1200000 | D16: 1800000 | E16: Fixe
A17: Hébergement Cloud AWS/GCP | B17: 100000 | C17: 250000 | D17: 500000 | E17: Variable (usage)
A18: APIs Intelligence Artificielle | B18: 80000 | C18: 200000 | D18: 400000 | E18: Variable (usage)
A19: Services tiers (Firebase, etc.) | B19: 40000 | C19: 80000 | D19: 120000 | E19: Variable
A20: Marketing & Acquisition | B20: 150000 | C20: 350000 | D20: 525000 | E20: Fixe/Variable
A21: Loyer & Co-working | B21: 100000 | C21: 150000 | D21: 200000 | E21: Fixe
A22: Télécom & Internet | B22: 30000 | C22: 40000 | D22: 50000 | E22: Fixe
A23: Frais divers & imprévus | B23: 50000 | C23: 80000 | D23: 100000 | E23: Variable
A24: TOTAL CHARGES MENSUELLES | B24: =SUM(B16:B23) -> 1230000 | C24: =SUM(C16:C23) -> 2350000 | D24: =SUM(D16:D23) -> 3695000
A25: C. INVESTISSEMENTS INITIAUX
A26: Élément | B26: Quantité | C26: Prix Unitaire (FCFA) | D26: Montant Total (FCFA) | E26: Amortissement
A27: Ordinateurs portables dev (i7, 16Go) | B27: 3 | C27: 350000 | D27: =B27*C27 -> 1050000 | E27: 3 ans
A28: Serveur NAS / Stockage local | B28: 1 | C28: 200000 | D28: =B28*C28 -> 200000 | E28: 5 ans
A29: Écrans 24" Full HD | B29: 3 | C29: 80000 | D29: =B29*C29 -> 240000 | E29: 5 ans
A30: Mobilier bureau | B30: 1 | C30: 210000 | D30: =B30*C30 -> 210000 | E30: 5 ans
A31: Infrastructure cloud initiale (setup) | B31: 1 | C31: 500000 | D31: =B31*C31 -> 500000 | E31: 1 an
A32: Licences logicielles & APIs (An 1) | B32: 1 | C32: 800000 | D32: =B32*C32 -> 800000 | E32: 1 an
A33: Frais de constitution SARL | B33: 1 | C33: 200000 | D33: =B33*C33 -> 200000 | E33: N/A
A34: TOTAL INVESTISSEMENTS | D34: =SUM(D27:D33) -> 3200000
A36: D. PLAN DE FINANCEMENT
A37: Source | B37: Montant (FCFA) | C37: % du total
A38: Apport personnel (numéraire) | B38: 2000000 | C38: =B38/SUM(B38:B40) -> 0.25974026
A39: Apport en nature (équipements) | B39: 1000000 | C39: =B39/SUM(B38:B40) -> 0.12987013
A40: Crédit/Subvention IJE-UniPod | B40: 4700000 | C40: =B40/SUM(B38:B40) -> 0.61038961
A41: TOTAL FINANCEMENT | B41: =SUM(B38:B40) -> 7700000

Sheet 6. Résumé Exécutif
A1: MURMURA — RÉSUMÉ EXÉCUTIF FINANCIER
A2: Messagerie Augmentée par l'IA | Lomé, Togo | Projet: 7 700 000 FCFA | Financement sollicité: 4 700 000 FCFA
A3: INDICATEUR CLÉ | B3: ANNÉE 1 — 2026 | C3: ANNÉE 2 — 2027 | D3: ANNÉE 3 — 2028
A4: Chiffre d'affaires | B4: 5400000 | C4: 42000000 | D4: 126000000
A5: Croissance CA | B5: — | C5: 678% | D5: 200%
A6: Marge brute | B6: 4020000 | C6: 37200000 | D6: 115200000
A7: Taux de marge brute | B7: 74,4% | C7: 88,6% | D7: 91,4%
A8: Charges d'exploitation totales | B8: 12360000 | C8: 22440000 | D8: 30300000
A9: EBITDA | B9: -7480000 | C9: 15620000 | D9: 85760000
A10: Résultat net | B10: -8282000 | C10: 8814000 | D10: 63184000
A11: Marge nette | B11: — | C11: 21,0% | D11: 50,1%
A12: Utilisateurs actifs payants | B12: 150 | C12: 1000 | D12: 5000
A13: Clients Business (B2B) | B13: 3 | C13: 20 | D13: 50
A14: Emplois créés (directs) | B14: 5 | C14: 8 | D14: 15
A15: Trésorerie de fin d'année | B15: 2300000 | C15: 12500000 | D15: 52000000
A17: ⚠️ Note: Le déficit de l'An 1 est structurel (phase d'amorçage). La rentabilité opérationnelle est attendue au cours du 7e mois d'exploitation.
